README.md
setup.cfg
setup.py
hl7_transform/__init__.py
hl7_transform/__main__.py
hl7_transform/field.py
hl7_transform/mapping.py
hl7_transform/message.py
hl7_transform/operations.py
hl7_transform/transform.py
hl7_transform.egg-info/PKG-INFO
hl7_transform.egg-info/SOURCES.txt
hl7_transform.egg-info/dependency_links.txt
hl7_transform.egg-info/entry_points.txt
hl7_transform.egg-info/requires.txt
hl7_transform.egg-info/top_level.txt
hl7_transform/test/__init__.py
hl7_transform/test/test_cli.py
hl7_transform/test/test_mapping.py
hl7_transform/test/test_message.py
hl7_transform/test/test_operations.py
hl7_transform/test/test_transform.py