Metadata-Version: 2.1
Name: hl7-transform
Version: 0.1.6
Summary: Library that transforms HL7 messages using mapping schemes
Home-page: https://github.com/pdyban/hl7_transform
Author: Pavlo Dyban (Doctolib GmbH)
Author-email: pavlo.dyban@doctolib.com
License: MIT
Download-URL: https://github.com/pdyban/hl7_transform/archive/v.0.1.6.tar.gz
Keywords: HL7,hospital IT,infrastructure,message,transform
Platform: UNKNOWN
Classifier: Development Status :: 4 - Beta
Classifier: Intended Audience :: System Administrators
Classifier: Intended Audience :: Developers
Classifier: Intended Audience :: Healthcare Industry
Classifier: Intended Audience :: Information Technology
Classifier: Intended Audience :: Telecommunications Industry
Classifier: License :: OSI Approved :: MIT License
Classifier: Programming Language :: Python :: 3
Classifier: Programming Language :: Python :: 3.4
Classifier: Programming Language :: Python :: 3.5
Classifier: Programming Language :: Python :: 3.6
Classifier: Programming Language :: Python :: 3.7
Classifier: Programming Language :: Python :: 3.8
Classifier: Programming Language :: Python :: 3.9
Classifier: Topic :: Communications
Classifier: Topic :: Software Development :: Libraries
Requires-Python: >=3
